{
  "summary": "The batch exhibits a variety of intents and styles, but there is significant redundancy in phrasing and sentence structure, particularly among negative and sarcastic reviews. Many texts utilize similar constructions and vocabulary, leading to a lack of nuanced expression.",
  "missing_modes": [
    "A more straightforward or plain English style that avoids complex metaphors or sarcasm.",
    "Unique combinations of attributes, such as 'positive' intent with 'hard' difficulty in a formal style."
  ],
  "overrepresented_modes": [
    "Sarcastic negative reviews that often follow a similar structure, particularly in their critique of emotional depth.",
    "Concise positive reviews that frequently use the phrase 'emotional depth' or variations thereof."
  ],
  "near_duplicate_rate": 0.25,
  "recommendations": [
    "Encourage the generation of more unique sentence structures and vocabulary to enhance nuance.",
    "Introduce prompts that specifically request diverse emotional expressions and avoid common phrases.",
    "Incorporate more edge cases or rare scenarios to challenge the generator's creativity."
  ],
  "coverage": {
    "intent": 1.0,
    "difficulty": 1.0,
    "polarity_intensity": 1.0,
    "style": 1.0,
    "noise": 1.0,
    "scenario_type": 1.0
  }
}